midas/modules/sbdata/__init__.py
midas/modules/sbdata/download.py
midas/modules/sbdata/meta.py
midas/modules/sbdata/module.py
midas/modules/sbdata/simulator.py
midas_sbdata-1.0.1.dist-info/LICENSE
midas_sbdata-1.0.1.dist-info/METADATA
midas_sbdata-1.0.1.dist-info/WHEEL
midas_sbdata-1.0.1.dist-info/top_level.txt
midas_sbdata-1.0.1.dist-info/RECORD
